systemqmonitor-1.0.2.dist-info/RECORD
systemqmonitor-1.0.2.dist-info/WHEEL
systemqmonitor-1.0.2.dist-info/METADATA
systemqmonitor-1.0.2.dist-info/top_level.txt
systemqmonitor/__init__.py
systemqmonitor/multiploter/dataset.cpython-38-x86_64-linux-gnu.so
systemqmonitor/multiploter/main.cpython-38-x86_64-linux-gnu.so
systemqmonitor/multiploter/ploter.cpython-38-x86_64-linux-gnu.so
systemqmonitor/multiploter/qt_compat.py
systemqmonitor/multiploter/event_queue.cpython-38-x86_64-linux-gnu.so
systemqmonitor/multiploter/config.py
systemqmonitor/multiploter/__init__.py
systemqmonitor/multiploter/toolbar.cpython-38-x86_64-linux-gnu.so
